uliweb_layout/__init__.py
uliweb_layout/form/README.md
uliweb_layout/form/__init__.py
uliweb_layout/form/form_helper.py
uliweb_layout/form/query_view.py
uliweb_layout/form/settings.ini
uliweb_layout/form/static/readme.txt
uliweb_layout/form/templates/readme.txt
uliweb_layout/layout/__init__.py
uliweb_layout/layout/config.ini
uliweb_layout/layout/detail_layout.py
uliweb_layout/layout/query_forms.py
uliweb_layout/layout/settings.ini
uliweb_layout/layout/static/layout.css
uliweb_layout/layout/static/readme.txt
uliweb_layout/layout/static/adminlte/2.3.12/css/AdminLTE.min.css
uliweb_layout/layout/static/adminlte/2.3.12/css/skins/_all-skins.min.css
uliweb_layout/layout/static/adminlte/2.3.12/js/app.min.js
uliweb_layout/layout/static/adminlte/2.3.2/css/AdminLTE.min.css
uliweb_layout/layout/static/adminlte/2.3.2/css/skins/_all-skins.css
uliweb_layout/layout/static/adminlte/2.3.2/css/skins/_all-skins.min.css
uliweb_layout/layout/static/adminlte/2.3.2/css/skins/skin-black-light.css
uliweb_layout/layout/static/adminlte/2.3.2/css/skins/skin-black-light.min.css
uliweb_layout/layout/static/adminlte/2.3.2/css/skins/skin-black.css
uliweb_layout/layout/static/adminlte/2.3.2/css/skins/skin-black.min.css
uliweb_layout/layout/static/adminlte/2.3.2/css/skins/skin-blue-light.css
uliweb_layout/layout/static/adminlte/2.3.2/css/skins/skin-blue-light.min.css
uliweb_layout/layout/static/adminlte/2.3.2/css/skins/skin-blue.css
uliweb_layout/layout/static/adminlte/2.3.2/css/skins/skin-blue.min.css
uliweb_layout/layout/static/adminlte/2.3.2/css/skins/skin-green-light.css
uliweb_layout/layout/static/adminlte/2.3.2/css/skins/skin-green-light.min.css
uliweb_layout/layout/static/adminlte/2.3.2/css/skins/skin-green.css
uliweb_layout/layout/static/adminlte/2.3.2/css/skins/skin-green.min.css
uliweb_layout/layout/static/adminlte/2.3.2/css/skins/skin-purple-light.css
uliweb_layout/layout/static/adminlte/2.3.2/css/skins/skin-purple-light.min.css
uliweb_layout-0.1.0.dist-info/METADATA
uliweb_layout-0.1.0.dist-info/WHEEL
uliweb_layout-0.1.0.dist-info/top_level.txt
uliweb_layout-0.1.0.dist-info/RECORD
